tnefparse/__init__.py
tnefparse/cmdline.py
tnefparse/codepage.py
tnefparse/mapi.py
tnefparse/properties.py
tnefparse/tnef.py
tnefparse/util.py
tnefparse-1.4.0.dist-info/LICENSE
tnefparse-1.4.0.dist-info/METADATA
tnefparse-1.4.0.dist-info/WHEEL
tnefparse-1.4.0.dist-info/entry_points.txt
tnefparse-1.4.0.dist-info/top_level.txt
tnefparse-1.4.0.dist-info/zip-safe
tnefparse-1.4.0.dist-info/RECORD
