Metadata-Version: 2.1
Name: tnefparse
Version: 1.4.0
Summary: a TNEF decoding library written in Python, without external dependencies
Home-page: https://github.com/koodaamo/tnefparse
Author: Petri Savolainen
Author-email: petri.savolainen@koodaamo.fi
License: LGPL
Keywords: TNEF MAPI decoding mail email microsoft
Platform: UNKNOWN
Classifier: Topic :: Communications :: Email
Classifier: License :: OSI Approved :: GNU Lesser General Public License v3 (LGPLv3)
Classifier: Intended Audience :: Developers
Classifier: Intended Audience :: End Users/Desktop
Classifier: Programming Language :: Python
Classifier: Programming Language :: Python :: 3
Classifier: Programming Language :: Python :: 3.6
Classifier: Programming Language :: Python :: 3.7
Classifier: Programming Language :: Python :: 3.8
Classifier: Programming Language :: Python :: 3.9
Classifier: Programming Language :: Python :: Implementation :: CPython
Classifier: Programming Language :: Python :: Implementation :: PyPy
Classifier: Development Status :: 5 - Production/Stable
Classifier: Environment :: Console
Provides-Extra: optional
